CargoZhongwenWendangFix1/README.md
CargoZhongwenWendangFix1/__init__.py
CargoZhongwenWendangFix1/__main__.py
CargoZhongwenWendangFix1/file.epub
CargoZhongwenWendangFix1/index.html
CargoZhongwenWendangFix1/css/__init__.py
CargoZhongwenWendangFix1/css/annotations.css
CargoZhongwenWendangFix1/css/main.css
CargoZhongwenWendangFix1/css/normalize.css
CargoZhongwenWendangFix1/css/popup.css
CargoZhongwenWendangFix1/font/__init__.py
CargoZhongwenWendangFix1/font/fontello.eot
CargoZhongwenWendangFix1/font/fontello.svg
CargoZhongwenWendangFix1/font/fontello.ttf
CargoZhongwenWendangFix1/font/fontello.woff
CargoZhongwenWendangFix1/img/__init__.py
CargoZhongwenWendangFix1/img/annotator-glyph-sprite.png
CargoZhongwenWendangFix1/img/annotator-icon-sprite.png
CargoZhongwenWendangFix1/img/apple-touch-icon.png
CargoZhongwenWendangFix1/img/cancelfullscreen.png
CargoZhongwenWendangFix1/img/close.png
CargoZhongwenWendangFix1/img/fullscreen.png
CargoZhongwenWendangFix1/img/loader.gif
CargoZhongwenWendangFix1/img/menu-icon.png
CargoZhongwenWendangFix1/img/save.png
CargoZhongwenWendangFix1/img/saved.png
CargoZhongwenWendangFix1/img/settings-s.png
CargoZhongwenWendangFix1/img/settings.png
CargoZhongwenWendangFix1/img/star.png
CargoZhongwenWendangFix1/js/__init__.py
CargoZhongwenWendangFix1/js/epub.js
CargoZhongwenWendangFix1/js/epub.min.js
CargoZhongwenWendangFix1/js/epub.min.map
CargoZhongwenWendangFix1/js/hooks.min.js
CargoZhongwenWendangFix1/js/hooks.min.map
CargoZhongwenWendangFix1/js/reader.js
CargoZhongwenWendangFix1/js/reader.js.map
CargoZhongwenWendangFix1/js/reader.min.js
CargoZhongwenWendangFix1/js/reader.min.map
CargoZhongwenWendangFix1/js/hooks/__init__.py
CargoZhongwenWendangFix1/js/hooks/extensions/__init__.py
CargoZhongwenWendangFix1/js/hooks/extensions/highlight.js
CargoZhongwenWendangFix1/js/libs/__init__.py
CargoZhongwenWendangFix1/js/libs/jquery.min.js
CargoZhongwenWendangFix1/js/libs/localforage.min.js
CargoZhongwenWendangFix1/js/libs/screenfull.js
cargo_zhongwen_wendang_fix1-2025.3.25.1.dist-info/METADATA
cargo_zhongwen_wendang_fix1-2025.3.25.1.dist-info/WHEEL
cargo_zhongwen_wendang_fix1-2025.3.25.1.dist-info/entry_points.txt
cargo_zhongwen_wendang_fix1-2025.3.25.1.dist-info/top_level.txt
cargo_zhongwen_wendang_fix1-2025.3.25.1.dist-info/RECORD
